hathi/__init__.py
hathi/__main__.py
hathi/filter_pass.py
hathi/mssql.py
hathi/mysql.py
hathi/postgres.py
hathi/scanner.py
hathi-1.7.0.dist-info/entry_points.txt
hathi-1.7.0.dist-info/LICENSE
hathi-1.7.0.dist-info/WHEEL
hathi-1.7.0.dist-info/METADATA
hathi-1.7.0.dist-info/RECORD
