Metadata-Version: 2.1
Name: hathi
Version: 1.7.0
Summary: A SQL host scanner and dictionary attack tool. Comes with a script (`filter_pass.py`) to filter a series of password lists based on password strength.
Author: Anthony Shaw
Classifier: License :: OSI Approved :: MIT License
Requires-Dist: asyncpg
Requires-Dist: rich
Requires-Dist: pymssql==2.1.5 ; extra == "mssql"
Requires-Dist: mysqlclient ; extra == "mysql"
Project-URL: Home, https://github.com/tonybaloney/hathi
Provides-Extra: mssql
Provides-Extra: mysql
